p3ui/__init__.py
p3ui/native.cp39-win_amd64.pyd
p3ui/skia.cp39-win_amd64.pyd
p3ui/binding/__init__.py
p3ui/binding/attribute_proxy.py
p3ui/binding/boolean_binding.py
p3ui/binding/color_attribute.py
p3ui/binding/enum_attribute.py
p3ui/binding/float_attribute.py
p3ui/binding/optional_attribute.py
p3ui/binding/string_attribute.py
p3ui/binding/unit_attribute.py
p3ui/core/__init__.py
p3ui/core/gui_event_loop.py
p3ui/core/run.py
p3ui/editor/__init__.py
p3ui/editor/__main__.py
p3ui/editor/_config.py
p3ui/editor/add_icon_dialog.py
p3ui/editor/add_node_dialog.py
p3ui/editor/attribute_editor.py
p3ui/editor/attribute_editor_factory.py
p3ui/editor/attribute_editor_template.py
p3ui/editor/definition.py
p3ui/editor/editor.py
p3ui/editor/editor_highlighting.py
p3ui/editor/editor_template.py
p3ui/editor/module_proxy.py
p3ui/editor/node_proxy.py
p3ui/editor/template_list_controller.py
p3ui/editor/template_tree_controller.py
p3ui/editor/template_tree_template.py
p3ui/editor/template_writer.py
p3ui/element/__init__.py
p3ui/element/color_util.py
p3ui/element/dialog.py
p3ui/element/icons.py
p3ui/element/image_surface.py
p3ui/element/image_viewer.py
p3ui/element/keyboard.py
p3ui/element/layout_viewer.py
p3ui/element/list_view.py
p3ui/element/model.py
p3ui/element/numpad.py
p3ui/element/repeater.py
p3ui/element/scrolled_column.py
p3ui/plot/__init__.py
p3ui/plot/_units.py
p3ui/plot/figure_canvas.py
p3ui/plot/figure_manager.py
p3ui/plot/graphics_context.py
p3ui/plot/make_font.py
p3ui/plot/matplotlib_surface.py
p3ui/plot/renderer.py
p3ui-1.1.6.dist-info/LICENSE
p3ui-1.1.6.dist-info/METADATA
p3ui-1.1.6.dist-info/WHEEL
p3ui-1.1.6.dist-info/top_level.txt
p3ui-1.1.6.dist-info/RECORD
