Metadata-Version: 2.1
Name: p3ui
Version: 1.1.6
Summary: Async Python User Interface Library
Home-page: https://github.com/0lru/p3ui
Author: 0lru
License-File: LICENSE
